ast_comments.py
ast_comments-1.2.1.dist-info/LICENSE
ast_comments-1.2.1.dist-info/METADATA
ast_comments-1.2.1.dist-info/WHEEL
ast_comments-1.2.1.dist-info/RECORD
