Metadata-Version: 2.1
Name: ast-comments
Version: 1.2.1
Summary: 
Home-page: https://github.com/t3rn0/ast-comments
License: MIT
Author: Dmitry Makarov
Author-email: dmtern0vnik@gmail.com
Requires-Python: >=3.8,<4.0
Classifier: License :: OSI Approved :: MIT License
Classifier: Programming Language :: Python :: 3
Classifier: Programming Language :: Python :: 3.8
Classifier: Programming Language :: Python :: 3.9
Classifier: Programming Language :: Python :: 3.10
Classifier: Programming Language :: Python :: 3.11
Project-URL: Repository, https://github.com/t3rn0/ast-comments
